universal_message/VERSION
universal_message/__init__.py
universal_message/_id.py
universal_message/utils/__init__.py
universal_message/utils/any_to_message.py
universal_message/utils/chat_cmpl_content_part_to_str.py
universal_message/utils/ensure_tz.py
universal_message/utils/is_response_input_file_param.py
universal_message/utils/is_response_input_image_param.py
universal_message/utils/is_response_input_message_content_list_param.py
universal_message/utils/is_response_input_text_param.py
universal_message/utils/is_response_output_text_param.py
universal_message/utils/messages_from_plaintext_of_gpt_oss.py
universal_message/utils/messages_to_sharegpt.py
universal_message/utils/response_input_content_to_str.py
universal_message/utils/return_openai_message.py
universal_message-0.5.0.dist-info/LICENSE
universal_message-0.5.0.dist-info/METADATA
universal_message-0.5.0.dist-info/WHEEL
universal_message-0.5.0.dist-info/RECORD
