Metadata-Version: 2.3
Name: universal-message
Version: 0.5.0
Summary: Message for Universal LLM Usage
License: MIT
Author: Allen Chou
Author-email: f1470891079@gmail.com
Requires-Python: >=3.11,<4
Classifier: License :: OSI Approved :: MIT License
Classifier: Programming Language :: Python :: 3
Classifier: Programming Language :: Python :: 3.11
Classifier: Programming Language :: Python :: 3.12
Classifier: Programming Language :: Python :: 3.13
Requires-Dist: dictpress (>=0.3.0)
Requires-Dist: durl-py (>=0.1.1)
Requires-Dist: json-repair
Requires-Dist: openai (>=1,<2)
Requires-Dist: openai-agents (>=0.1.0,<1.0.0)
Requires-Dist: pydantic (>=2)
Requires-Dist: str-or-none
Project-URL: Homepage, https://github.com/allen2c/universal-message
Project-URL: PyPI, https://pypi.org/project/universal-message/
Project-URL: Repository, https://github.com/allen2c/universal-message
